README
setup.py
biribiri/__init__.py
biribiri.rpc.client.egg-info/PKG-INFO
biribiri.rpc.client.egg-info/SOURCES.txt
biribiri.rpc.client.egg-info/dependency_links.txt
biribiri.rpc.client.egg-info/requires.txt
biribiri.rpc.client.egg-info/top_level.txt
biribiri/rpc/__init__.py
biribiri/rpc/client/__init__.py
biribiri/rpc/client/client.py