Metadata-Version: 1.0
Name: biribiri.rpc.client
Version: 0.1
Summary: Simple client class for accessing JSON rpc web-servers
Home-page: http://biribiri.enodev.org
Author: Ilya Petrov
Author-email: ilya.muromec@gmail.com
License: BSDL
Platform: UNKNOWN
